dataframe_textual/__init__.py
dataframe_textual/__main__.py
dataframe_textual/common.py
dataframe_textual/data_frame_help_panel.py
dataframe_textual/data_frame_table.py
dataframe_textual/data_frame_viewer.py
dataframe_textual/sql_screen.py
dataframe_textual/table_screen.py
dataframe_textual/yes_no_screen.py
dataframe_textual-2.10.1.dist-info/METADATA
dataframe_textual-2.10.1.dist-info/WHEEL
dataframe_textual-2.10.1.dist-info/entry_points.txt
dataframe_textual-2.10.1.dist-info/licenses/LICENSE
dataframe_textual-2.10.1.dist-info/RECORD
