Metadata-Version: 2.4
Name: dataframe-textual
Version: 2.10.1
Summary: Interactive terminal viewer/editor for tabular data
Project-URL: Homepage, https://github.com/need47/dataframe-textual
Project-URL: Repository, https://github.com/need47/dataframe-textual.git
Project-URL: Documentation, https://github.com/need47/dataframe-textual#readme
Project-URL: Bug Tracker, https://github.com/need47/dataframe-textual/issues
Author-email: Tiejun Cheng <need47@gmail.com>
License: MIT
License-File: LICENSE
Keywords: csv,data-analysis,editor,excel,interactive,polars,terminal,textual,tui,viewer
Classifier: Development Status :: 3 - Alpha
Classifier: Environment :: Console
Classifier: Intended Audience :: Developers
Classifier: Intended Audience :: End Users/Desktop
Classifier: License :: OSI Approved :: MIT License
Classifier: Natural Language :: English
Classifier: Operating System :: MacOS
Classifier: Operating System :: POSIX
Classifier: Operating System :: Unix
Classifier: Programming Language :: Python :: 3
Classifier: Programming Language :: Python :: 3.11
Classifier: Programming Language :: Python :: 3.12
Classifier: Programming Language :: Python :: 3.13
Classifier: Programming Language :: Python :: 3.14
Classifier: Topic :: Office/Business
Classifier: Topic :: Utilities
Classifier: Typing :: Typed
Requires-Python: >=3.11
Requires-Dist: polars>=1.34.0
Requires-Dist: textual[syntax]>=6.5.0
Provides-Extra: dev
Requires-Dist: textual-dev>=1.8.0; extra == 'dev'
Provides-Extra: excel
Requires-Dist: fastexcel>=0.16.0; extra == 'excel'
Requires-Dist: xlsxwriter>=3.2.9; extra == 'excel'
